likeshell/__init__.py
likeshell/__version__.py
likeshell/comment.py
likeshell/console.py
likeshell/context.py
likeshell/decoration.py
likeshell/definition.py
likeshell/exceptions.py
likeshell/options.py
likeshell/shell.py
likeshell/typehints.py
likeshell/types.py
likeshell/util.py
likeshell-1.1.5.dist-info/LICENSE
likeshell-1.1.5.dist-info/METADATA
likeshell-1.1.5.dist-info/WHEEL
likeshell-1.1.5.dist-info/top_level.txt
likeshell-1.1.5.dist-info/RECORD
