Metadata-Version: 2.1
Name: likeshell
Version: 1.1.5
Summary: 快速构建一个干净整洁的命令行工具包。Quickly develop your command line interface(CLI) toolkit.
Home-page: https://github.com/Orisdaddy/likeshell
Author: Fizone
Author-email: edeport126@gmail.com
License: Apache License 2.0
Keywords: shell,command,line,cli
Platform: any
Classifier: Development Status :: 5 - Production/Stable
Classifier: Intended Audience :: Developers
Classifier: License :: OSI Approved :: Apache Software License
Classifier: Programming Language :: Python
Classifier: Programming Language :: Python :: 3
Classifier: Programming Language :: Python :: 3.6
Classifier: Programming Language :: Python :: 3.7
Classifier: Programming Language :: Python :: 3.8
Classifier: Programming Language :: Python :: 3.9
Requires-Python: >=3.6
